lm_pelican_quarto-0.4.0.dist-info/METADATA
lm_pelican_quarto-0.4.0.dist-info/WHEEL
lm_pelican_quarto-0.4.0.dist-info/entry_points.txt
lm_pelican_quarto-0.4.0.dist-info/licenses/LICENSE
pelican/plugins/lm_pelican_quarto/__init__.py
pelican/plugins/lm_pelican_quarto/adapters.py
pelican/plugins/lm_pelican_quarto/parsers.py
pelican/plugins/lm_pelican_quarto/quarto.py
pelican/plugins/lm_pelican_quarto/readers.py
pelican/plugins/lm_pelican_quarto/tests/__init__.py
pelican/plugins/lm_pelican_quarto/tests/test_quarto.py
lm_pelican_quarto-0.4.0.dist-info/RECORD
