Metadata-Version: 2.1
Name: lm-pelican-quarto
Version: 0.4.0
Summary: A plugin for integrating Quarto reports in your Pelican articles.
Keywords: python,R,Quarto,data science,Rmarkdown,ggplot2,tidyverse,dplyr
Author-Email: Lukas Muenter <lukas.muenter@protonmail.com>
License: MIT
Classifier: Development Status :: 1 - Planning
Classifier: Environment :: Console
Classifier: Framework :: Pelican
Classifier: Framework :: Pelican :: Plugins
Classifier: Intended Audience :: End Users/Desktop
Classifier: License :: OSI Approved :: MIT License
Classifier: Operating System :: OS Independent
Classifier: Programming Language :: Python :: 3
Classifier: Programming Language :: Python :: 3.8
Classifier: Programming Language :: Python :: 3.9
Classifier: Programming Language :: Python :: 3.10
Classifier: Programming Language :: Python :: 3.11
Classifier: Programming Language :: Python :: 3.12
Classifier: Topic :: Internet :: WWW/HTTP
Classifier: Topic :: Software Development :: Libraries :: Python Modules
Project-URL: Homepage, https://github.com/lmuenter/pelican-quarto
Project-URL: Issue tracker, https://github.com/lmuenter/pelican-quarto/issues
Project-URL: Funding, https://donate.getpelican.com/
Requires-Python: <4.0,>=3.8.1
Requires-Dist: pelican>=4.5
Requires-Dist: pyYAML>=6.0
Requires-Dist: markdown>=3.4
Requires-Dist: beautifulsoup4>=4.0
Provides-Extra: markdown
Requires-Dist: markdown>=3.4; extra == "markdown"
